sythonlab_cubacel_sdk/__init__.py
sythonlab_cubacel_sdk/constants.py
sythonlab_cubacel_sdk/sdk.py
sythonlab_cubacel_sdk/sdk_config.py
sythonlab_cubacel_sdk-1.0.0.dist-info/METADATA
sythonlab_cubacel_sdk-1.0.0.dist-info/WHEEL
sythonlab_cubacel_sdk-1.0.0.dist-info/top_level.txt
sythonlab_cubacel_sdk-1.0.0.dist-info/RECORD
