Metadata-Version: 2.4
Name: sythonlab_cubacel_sdk
Version: 1.0.0
Summary: SDK para la integración con Cubacel
Home-page: https://github.com/sythonlab/SythonLab-Cubacel-SDK
Author: José Angel Alvarez Abraira
Author-email: sythonlab@gmail.com
Classifier: Development Status :: 3 - Alpha
Classifier: Intended Audience :: Developers
Classifier: Programming Language :: Python :: 3
Classifier: Programming Language :: Python :: 3.7
Classifier: Programming Language :: Python :: 3.8
Classifier: Programming Language :: Python :: 3.9
Requires-Python: >=3.8
Requires-Dist: requests
Requires-Dist: zeep
Requires-Dist: setuptools
Dynamic: author
Dynamic: author-email
Dynamic: classifier
Dynamic: description
Dynamic: description-content-type
Dynamic: home-page
Dynamic: requires-dist
Dynamic: requires-python
Dynamic: summary
